{
  "project_info": {
    "project_number": "538135893912",
    "project_id": "filmproject-9a47d",
    "storage_bucket": "filmproject-9a47d.appspot.com"
  },
  "client": [
    {
      "client_info": {
        "mobilesdk_app_id": "1:538135893912:android:ca9e1de0f1d4ed426bfded",
        "android_client_info": {
          "package_name": "com.pavelprojects.filmlibraryproject"
        }
      },
      "oauth_client": [
        {
          "client_id": "538135893912-rgdfq70qatbu1km00d97jqu5ag2s2itn.apps.googleusercontent.com",
          "client_type": 3
        }
      ],
      "api_key": [
        {
          "current_key": "AIzaSyAPAN4mN0NXEvqaLJ1tELfEnDCRsutlalY"
        }
      ],
      "services": {
        "appinvite_service": {
          "other_platform_oauth_client": [
            {
              "client_id": "538135893912-rgdfq70qatbu1km00d97jqu5ag2s2itn.apps.googleusercontent.com",
              "client_type": 3
            }
          ]
        }
      }
    }
  ],
  "configuration_version": "1"
}